cdo/__init__.py
cdo/cdo.py
cdo-1.6.1.dist-info/METADATA
cdo-1.6.1.dist-info/WHEEL
cdo-1.6.1.dist-info/top_level.txt
cdo-1.6.1.dist-info/RECORD
