Metadata-Version: 2.1
Name: cdo
Version: 1.6.1
Summary: python bindings to CDO
Home-page: https://code.mpimet.mpg.de/projects/cdo/wiki/Cdo%7Brbpy%7D
Author: Ralf Mueller
Author-email: stark.dreamdetective@gmail.com
Classifier: License :: OSI Approved :: BSD License
Classifier: Programming Language :: Python
Classifier: Programming Language :: Python :: 3
Classifier: Programming Language :: Python :: 2.7
Classifier: Programming Language :: Python :: Implementation :: CPython
Classifier: Programming Language :: Python :: Implementation :: PyPy
Requires-Python: >=2.7.0
Requires-Dist: six
Requires-Dist: packaging
Provides-Extra: numpy_output
Requires-Dist: netCDF4 ; extra == 'numpy_output'
Provides-Extra: xarray_output
Requires-Dist: xarray ; extra == 'xarray_output'
